coincap/__init__.py
coincap-1.0.dist-info/METADATA
coincap-1.0.dist-info/RECORD
coincap-1.0.dist-info/WHEEL
coincap-1.0.dist-info/top_level.txt
