Metadata-Version: 2.1
Name: coincap
Version: 1.0
Summary: A small package for history data of crypto currency
Home-page: https://github.com/BurgessFANG/coincap
Author: jaicuo
Author-email: 448117031@qq.com
License: UNKNOWN
Platform: UNKNOWN
Classifier: Programming Language :: Python :: 3
Classifier: License :: OSI Approved :: MIT License
Classifier: Operating System :: OS Independent
